INSTALL.rst
LICENSE
MANIFEST.in
README.rst
VERSION
requirements.txt
setup.py
tasks.py
src/plagiarism/__init__.py
src/plagiarism/__main__.py
src/plagiarism/__meta__.py
src/plagiarism/bag_of_words.py
src/plagiarism/clusterization.py
src/plagiarism/core.py
src/plagiarism/fixtures.py
src/plagiarism/input.py
src/plagiarism/math_utils.py
src/plagiarism/ngrams.py
src/plagiarism/stopwords.py
src/plagiarism/tasks.py
src/plagiarism/text.py
src/plagiarism/text_distances.py
src/plagiarism/tokenizers.py
src/plagiarism/tokens.py
src/plagiarism/utils.py
src/plagiarism.egg-info/PKG-INFO
src/plagiarism.egg-info/SOURCES.txt
src/plagiarism.egg-info/dependency_links.txt
src/plagiarism.egg-info/entry_points.txt
src/plagiarism.egg-info/not-zip-safe
src/plagiarism.egg-info/requires.txt
src/plagiarism.egg-info/top_level.txt
src/plagiarism/tests/__init__.py
src/plagiarism/tests/__main__.py
src/plagiarism/tests/conftest.py
src/plagiarism/tests/test_bag_of_words.py
src/plagiarism/tests/test_documentation.py
src/plagiarism/tests/test_inputs.py
src/plagiarism/tests/test_math_utils.py
src/plagiarism/tests/test_ngrams.py
src/plagiarism/tests/test_plagiarism.py
src/plagiarism/tests/test_stop_words.py
src/plagiarism/tests/test_text.py
src/plagiarism/tests/test_tokenizers.py
src/plagiarism/tests/test_utils.py